sitwatch/__init__.py
sitwatch-1.0.2.dist-info/LICENSE
sitwatch-1.0.2.dist-info/METADATA
sitwatch-1.0.2.dist-info/WHEEL
sitwatch-1.0.2.dist-info/top_level.txt
sitwatch-1.0.2.dist-info/RECORD
